llama_index/__init__.py
llama_index/readers/__init__.py
llama_index/readers/builtsimple/__init__.py
llama_index/readers/builtsimple/arxiv.py
llama_index/readers/builtsimple/base.py
llama_index/readers/builtsimple/pubmed.py
llama_index/readers/builtsimple/wikipedia.py
llama_index_readers_builtsimple-0.1.0.dist-info/METADATA
llama_index_readers_builtsimple-0.1.0.dist-info/WHEEL
llama_index_readers_builtsimple-0.1.0.dist-info/licenses/LICENSE
llama_index_readers_builtsimple-0.1.0.dist-info/RECORD
