Metadata-Version: 2.4
Name: llama-index-readers-builtsimple
Version: 0.1.0
Summary: LlamaIndex readers for Built-Simple research APIs (PubMed, ArXiv, Wikipedia)
License: MIT
License-File: LICENSE
Keywords: llama-index,research,pubmed,arxiv,wikipedia,academic,papers
Author: Built-Simple
Author-email: contact@built-simple.ai
Requires-Python: >=3.9,<4.0
Classifier: Development Status :: 4 - Beta
Classifier: Intended Audience :: Developers
Classifier: Intended Audience :: Science/Research
Classifier: License :: OSI Approved :: MIT License
Classifier: Operating System :: OS Independent
Classifier: Programming Language :: Python :: 3
Classifier: Programming Language :: Python :: 3.9
Classifier: Programming Language :: Python :: 3.10
Classifier: Programming Language :: Python :: 3.11
Classifier: Programming Language :: Python :: 3.12
Classifier: Programming Language :: Python :: 3.13
Classifier: Programming Language :: Python :: 3.14
Classifier: Topic :: Scientific/Engineering
Classifier: Topic :: Scientific/Engineering :: Artificial Intelligence
Provides-Extra: dev
Requires-Dist: llama-index-core (>=0.10.0)
Requires-Dist: requests (>=2.28.0)
Project-URL: Documentation, https://docs.llamaindex.ai
Project-URL: Homepage, https://built-simple.ai
Project-URL: Repository, https://github.com/run-llama/llama_index
